queue_broker_client/__init__.py
queue_broker_client/broker.py
queue_broker_client-0.0.5.dist-info/LICENSE
queue_broker_client-0.0.5.dist-info/METADATA
queue_broker_client-0.0.5.dist-info/WHEEL
queue_broker_client-0.0.5.dist-info/top_level.txt
queue_broker_client-0.0.5.dist-info/RECORD
