Metadata-Version: 2.1
Name: queue_broker_client
Version: 0.0.5
Summary: A package to make the creation of queue consumers easier
Home-page: https://github.com/max-wickham/flask_queues
Author: Max Wickham
Author-email: maxwickhammonro@gmail.com
License: UNKNOWN
Platform: UNKNOWN
Classifier: Programming Language :: Python :: 3
Classifier: License :: OSI Approved :: MIT License
Classifier: Operating System :: OS Independent
Requires-Python: >=3.6
License-File: LICENSE
